<annotation>
	<folder>unknown</folder>
	<filename>toczekor_pos_004.jpg</filename>
	<path>toczekor_pos_004.jpg</path>
	<source>
		<database>Unknown</database>
	</source>
	<size>
		<width>1152</width>
		<height>864</height>
		<depth>3</depth>
	</size>
	<segmented>0</segmented>
	<object>
		<name>ecocup</name>
		<pose>Unspecified</pose>
		<truncated>0</truncated>
		<difficult>0</difficult>
		<bndbox>
			<xmin>92</xmin>
			<ymin>352</ymin>
			<xmax>307</xmax>
			<ymax>734</ymax>
		</bndbox>
	</object>
	<object>
		<name>ecocup</name>
		<pose>Unspecified</pose>
		<truncated>0</truncated>
		<difficult>0</difficult>
		<bndbox>
			<xmin>481</xmin>
			<ymin>352</ymin>
			<xmax>671</xmax>
			<ymax>708</ymax>
		</bndbox>
	</object>
</annotation>
